{
  "$schema": "https://raw.githubusercontent.com/badlogic/pi-mono/main/packages/coding-agent/src/modes/interactive/theme/theme-schema.json",
  "name": "power-dark",
  "vars": {
    "bg0": "#0b1020",
    "bg1": "#111827",
    "bg2": "#1f2937",
    "fg": "#e5e7eb",
    "muted": "#94a3b8",
    "dim": "#64748b",
    "cyan": "#22d3ee",
    "blue": "#60a5fa",
    "violet": "#a78bfa",
    "green": "#34d399",
    "yellow": "#fbbf24",
    "orange": "#fb923c",
    "red": "#fb7185"
  },
  "colors": {
    "accent": "cyan",
    "border": "blue",
    "borderAccent": "cyan",
    "borderMuted": "dim",
    "success": "green",
    "error": "red",
    "warning": "yellow",
    "muted": "muted",
    "dim": "dim",
    "text": "fg",
    "thinkingText": "muted",
    "selectedBg": "bg2",
    "userMessageBg": "#172033",
    "userMessageText": "fg",
    "customMessageBg": "#151b2c",
    "customMessageText": "fg",
    "customMessageLabel": "violet",
    "toolPendingBg": "#101827",
    "toolSuccessBg": "#0f231d",
    "toolErrorBg": "#2a1218",
    "toolTitle": "cyan",
    "toolOutput": "fg",
    "mdHeading": "yellow",
    "mdLink": "cyan",
    "mdLinkUrl": "muted",
    "mdCode": "green",
    "mdCodeBlock": "fg",
    "mdCodeBlockBorder": "dim",
    "mdQuote": "muted",
    "mdQuoteBorder": "dim",
    "mdHr": "dim",
    "mdListBullet": "cyan",
    "toolDiffAdded": "green",
    "toolDiffRemoved": "red",
    "toolDiffContext": "muted",
    "syntaxComment": "dim",
    "syntaxKeyword": "violet",
    "syntaxFunction": "blue",
    "syntaxVariable": "orange",
    "syntaxString": "green",
    "syntaxNumber": "yellow",
    "syntaxType": "cyan",
    "syntaxOperator": "violet",
    "syntaxPunctuation": "muted",
    "thinkingOff": "dim",
    "thinkingMinimal": "blue",
    "thinkingLow": "cyan",
    "thinkingMedium": "green",
    "thinkingHigh": "violet",
    "thinkingXhigh": "red",
    "bashMode": "yellow"
  },
  "export": {
    "pageBg": "#0b1020",
    "cardBg": "#111827",
    "infoBg": "#172033"
  }
}
